abandoned_butterfly/__init__.py
abandoned_butterfly/dl.py
abandoned_butterfly/tn.py
abandoned_butterfly-0.0.2.dist-info/LICENSE
abandoned_butterfly-0.0.2.dist-info/METADATA
abandoned_butterfly-0.0.2.dist-info/WHEEL
abandoned_butterfly-0.0.2.dist-info/top_level.txt
abandoned_butterfly-0.0.2.dist-info/RECORD
