Metadata-Version: 2.1
Name: abandoned-butterfly
Version: 0.0.2
Summary: A small package that contains all the source code of deep learning practicles
Home-page: https://github.com/abhi3940/abandoned_butterfly
Author: abhi
Author-email: savaleabhijeet@gmail.com
Project-URL: Bug Tracker, https://github.com/abhi3940/abandoned_butterfly/issues
Classifier: Programming Language :: Python :: 3
Classifier: License :: OSI Approved :: MIT License
Classifier: Operating System :: OS Independent
Requires-Python: >=3.6
License-File: LICENSE
